{
  "main": {
    "id": "178c9966d8dcdea5",
    "type": "split",
    "children": [
      {
        "id": "78615b9d35848e39",
        "type": "tabs",
        "children": [
          {
            "id": "e8cfec7e513cec98",
            "type": "leaf",
            "state": {
              "type": "markdown",
              "state": {
                "file": "1 - Poems/A Dreaming Owl Unbound.md",
                "mode": "source",
                "source": false
              },
              "icon": "lucide-file",
              "title": "A Dreaming Owl Unbound"
            }
          },
          {
            "id": "647fc0733d338d4c",
            "type": "leaf",
            "state": {
              "type": "full-calendar-view",
              "state": {},
              "icon": "calendar-glyph",
              "title": "Calendar"
            }
          },
          {
            "id": "8cc73e797fdc693a",
            "type": "leaf",
            "state": {
              "type": "mk-space",
              "state": {
                "path": "textgenerator/templates/default"
              },
              "icon": "lucide-file",
              "title": "default"
            }
          }
        ],
        "currentTab": 2
      }
    ],
    "direction": "vertical"
  },
  "left": {
    "id": "91c660cbea56a0c1",
    "type": "split",
    "children": [
      {
        "id": "ed06890360d3cefa",
        "type": "tabs",
        "children": [
          {
            "id": "118a9d6d6fa7bbb7",
            "type": "leaf",
            "state": {
              "type": "file-explorer",
              "state": {
                "sortOrder": "alphabetical",
                "autoReveal": false
              },
              "icon": "lucide-folder-closed",
              "title": "Files"
            }
          },
          {
            "id": "971127fb5853f820",
            "type": "leaf",
            "state": {
              "type": "search",
              "state": {
                "query": "",
                "matchingCase": false,
                "explainSearch": false,
                "collapseAll": false,
                "extraContext": false,
                "sortOrder": "alphabetical"
              },
              "icon": "lucide-search",
              "title": "Search"
            }
          },
          {
            "id": "4ee211529a439058",
            "type": "leaf",
            "state": {
              "type": "bookmarks",
              "state": {},
              "icon": "lucide-bookmark",
              "title": "Bookmarks"
            }
          },
          {
            "id": "30f854f9109278c0",
            "type": "leaf",
            "state": {
              "type": "mk-path-view",
              "state": {},
              "icon": "layout-grid",
              "title": "Navigator"
            }
          }
        ],
        "currentTab": 3
      }
    ],
    "direction": "horizontal",
    "width": 200
  },
  "right": {
    "id": "1aaefb1cd89b23ab",
    "type": "split",
    "children": [
      {
        "id": "554690119c9446aa",
        "type": "tabs",
        "children": [
          {
            "id": "56f0bf59c4b7ecd3",
            "type": "leaf",
            "state": {
              "type": "backlink",
              "state": {
                "file": "4 - Diary/2025-02-24.md",
                "collapseAll": false,
                "extraContext": false,
                "sortOrder": "alphabetical",
                "showSearch": false,
                "searchQuery": "",
                "backlinkCollapsed": false,
                "unlinkedCollapsed": true
              },
              "icon": "links-coming-in",
              "title": "Backlinks for 2025-02-24"
            }
          },
          {
            "id": "112c5b16cbc6d73d",
            "type": "leaf",
            "state": {
              "type": "outgoing-link",
              "state": {
                "file": "4 - Diary/2025-02-24.md",
                "linksCollapsed": false,
                "unlinkedCollapsed": true
              },
              "icon": "links-going-out",
              "title": "Outgoing links from 2025-02-24"
            }
          },
          {
            "id": "1d76227f27895c98",
            "type": "leaf",
            "state": {
              "type": "tag",
              "state": {
                "sortOrder": "frequency",
                "useHierarchy": true,
                "showSearch": false,
                "searchQuery": ""
              },
              "icon": "lucide-tags",
              "title": "Tags"
            }
          },
          {
            "id": "cd28c09edfc0377f",
            "type": "leaf",
            "state": {
              "type": "outline",
              "state": {
                "file": "4 - Diary/2025-02-24.md",
                "followCursor": false,
                "showSearch": false,
                "searchQuery": ""
              },
              "icon": "lucide-list",
              "title": "Outline of 2025-02-24"
            }
          }
        ]
      }
    ],
    "direction": "horizontal",
    "width": 300,
    "collapsed": true
  },
  "left-ribbon": {
    "hiddenItems": {
      "switcher:Open quick switcher": false,
      "graph:Open graph view": false,
      "canvas:Create new canvas": false,
      "daily-notes:Open today's daily note": false,
      "templates:Insert template": false,
      "command-palette:Open command palette": false,
      "obsidian-textgenerator-plugin:Generate Text!": false,
      "obsidian-textgenerator-plugin:Text Generator: Templates Packages Manager": false,
      "obsidian-full-calendar:Open Full Calendar": false
    }
  },
  "active": "8cc73e797fdc693a",
  "lastOpenFiles": [
    "Untitled.md",
    "6 - Calendar/6 - Calendar.md",
    "6 - Calendar",
    "3 - Moments/2025-03-10 Read Scientism.md",
    "1 - Poems/A Dreaming Owl Unbound.md",
    "2 - Essays/The Book of Thel.md",
    "3 - Moments/2025-03-02 Illusory Summer.md",
    "textgenerator/templates/default/simplify.md",
    "textgenerator/templates/default/getIdeas.md",
    "textgenerator/templates/default/getOutline.md",
    "textgenerator/templates/default/summarize.md",
    "textgenerator/templates/default/rewrite.md",
    "textgenerator/templates/default/getEmailNeg.md",
    "textgenerator/templates/default/getParagraph.md",
    "textgenerator/templates/default/summarizeLarge.md",
    "textgenerator/templates/default/getTitles.md",
    "textgenerator/templates/default/getTags.md",
    "textgenerator/templates/default/getEmailPos.md",
    "textgenerator/templates/default",
    "textgenerator/templates",
    "textgenerator",
    "2 - Essays/Reflection.md",
    "2 - Essays/Death and Rebirth.md",
    "2 - Essays/Luminescence.md",
    "2 - Essays/The Tale of Fallen Angels - On Frankenstein.md",
    "2 - Essays/会饮篇.md",
    "4 - Source Material/Articles/Scientism.md",
    "2 - Essays/A Guide on How to Use this System.md",
    "1 - Poems/骨笛.md",
    "1 - Poems/颂太阳.md",
    "Tags",
    "1 - Poems/20231003_151734.jpg",
    "1 - Poems/20250111_091608.jpg",
    "1 - Poems/20250104_172502.jpg",
    "1 - Poems/20240614_181823.jpg",
    "6 - Daily Logs",
    "6 - Catalogues",
    "Pasted image 20250225224736.png",
    "5 - Templates"
  ]
}